__init__.py
main.py
dalaipy-2.0.2.dist-info/LICENSE
dalaipy-2.0.2.dist-info/METADATA
dalaipy-2.0.2.dist-info/WHEEL
dalaipy-2.0.2.dist-info/top_level.txt
dalaipy-2.0.2.dist-info/RECORD
