Metadata-Version: 2.1
Name: dalaipy
Version: 2.0.2
Summary: A Python Wrapper for Dalai
Author-email: William Stella <william.a.stella@gmail.com>
Project-URL: Homepage, https://github.com/wastella/dalaipy
Project-URL: Bug Tracker, https://github.com/wastella/dalaipy/issues
Classifier: Programming Language :: Python :: 3
Classifier: License :: OSI Approved :: MIT License
Classifier: Operating System :: OS Independent
Requires-Python: >=3.7
License-File: LICENSE
Requires-Dist: python-socketio
